[
    {
        "author"      : "Tobias Uhlig",
        "authorImage" : "author_TobiasUhlig.jpeg",
        "date"        : "Jul 12, 2024",
        "id"          : 59,
        "image"       : "transform_dom_tree.png",
        "name"        : "A blazing-fast algorithm to transform one DOM tree into another",
        "provider"    : "Medium",
        "publisher"   : "ITNEXT",
        "selectedInto": [],
        "type"        : "Blog Post",
        "url"         : "https://itnext.io/a-blazing-fast-algorithm-to-transform-one-dom-tree-into-another-4ff9c934bc49?source=friends_link&sk=f1de46dbd464095b8d0b0a271644cb75"
    },
    {
        "author"      : "Tobias Uhlig",
        "authorImage" : "author_TobiasUhlig.jpeg",
        "date"        : "Jun 17, 2024",
        "id"          : 58,
        "image"       : "Sharing_real_time_data.png",
        "name"        : "Sharing real-time WebSocket data across multiple browser windows",
        "provider"    : "Medium",
        "publisher"   : "ITNEXT",
        "selectedInto": [],
        "type"        : "Blog Post",
        "url"         : "https://itnext.io/sharing-real-time-websocket-data-across-multiple-browser-windows-4e0538dd7563?source=friends_link&sk=9efb3e4f38c82fb3e04899c61bb5fcb8"
    },
    {
        "author"      : "Torsten Dinkheller",
        "authorImage" : "author_TorstenDinkheller.jpg",
        "date"        : "Feb 03, 2023",
        "id"          : 57,
        "image"       : "overrides-medium.jpg",
        "name"        : "Leveraging Overrides for Resilient Customizations and Effective Bugfixes in JavaScript Frameworks",
        "provider"    : "Medium",
        "publisher"   : "ITNEXT",
        "selectedInto": [],
        "type"        : "Blog Post",
        "url"         : "https://itnext.io/leveraging-overrides-for-resilient-customizations-and-effective-bugfixes-in-javascript-frameworks-5b8ccfec0f8?source=friends_link&sk=790e868aac8b8570f0eee093adc30c00"
    },
    {
        "author"      : "Torsten Dinkheller",
        "authorImage" : "author_TorstenDinkheller.jpg",
        "date"        : "Jan 28, 2023",
        "id"          : 56,
        "image"       : "toast-tutorial-medium.jpg",
        "name"        : "Reusable Next Gen Toast — to Industry Standard",
        "provider"    : "Medium",
        "publisher"   : "ITNEXT",
        "selectedInto": [],
        "type"        : "Blog Post",
        "url"         : "https://itnext.io/reusable-next-gen-toast-to-industry-standard-502d2950701f?source=friends_link&sk=f74ba5b5161986d9d8dec6e91ba11a5b"
    },
    {
        "author"      : "Tobias Uhlig",
        "authorImage" : "author_TobiasUhlig.jpeg",
        "date"        : "Jan 25, 2023",
        "id"          : 55,
        "image"       : "the-next-generation-of-front-end-development.png",
        "name"        : "The Next Generation of Front-end Development",
        "provider"    : "Medium",
        "publisher"   : "ITNEXT",
        "selectedInto": [],
        "type"        : "Blog Post",
        "url"         : "https://itnext.io/the-next-generation-of-front-end-development-65887c59b173?source=friends_link&sk=51654f60033120e84454791015d8d205"
    },
    {
        "author"      : "Tobias Uhlig",
        "authorImage" : "author_TobiasUhlig.jpeg",
        "date"        : "Jan 18, 2023",
        "id"          : 54,
        "image"       : "changing-scoped-css-variables-using-javascript.png",
        "name"        : "Changing scoped CSS variables using JavaScript",
        "provider"    : "Medium",
        "publisher"   : "ITNEXT",
        "selectedInto": [],
        "type"        : "Blog Post",
        "url"         : "https://itnext.io/changing-scoped-css-variables-using-javascript-96b26dfa43b1?source=friends_link&sk=2be526c9917418b21fe42bd66c40ea87"
    },
    {
        "author"      : "Tobias Uhlig",
        "authorImage" : "author_TobiasUhlig.jpeg",
        "date"        : "Sep 07, 2022",
        "id"          : 53,
        "image"       : "the-secret-of-successfully-using-multi-window-webgl-canvas.png",
        "name"        : "The secret of successfully using multi window WebGL Canvas",
        "provider"    : "Medium",
        "publisher"   : "ITNEXT",
        "selectedInto": [],
        "type"        : "Blog Post",
        "url"         : "https://itnext.io/the-secret-of-successfully-using-multi-window-webgl-canvas-5a2d05555ad1?source=friends_link&sk=d24ec0ec25aa6678d5fd1f59aaf09007"
    },
    {
        "author"      : "Tobias Uhlig",
        "authorImage" : "author_TobiasUhlig.jpeg",
        "date"        : "Apr 13, 2022",
        "id"          : 52,
        "image"       : "safari-now-fully-supports-sharedworkers.png",
        "name"        : "Safari now fully supports SharedWorkers",
        "provider"    : "Medium",
        "publisher"   : "ITNEXT",
        "selectedInto": [],
        "type"        : "Blog Post",
        "url"         : "https://itnext.io/safari-now-fully-supports-sharedworkers-534733b56b4c?source=friends_link&sk=97b83b39629cf79dbe8feff0042c19b3"
    },
    {
        "author"      : "Tobias Uhlig",
        "authorImage" : "author_TobiasUhlig.jpeg",
        "date"        : "Mar 28, 2022",
        "id"          : 51,
        "image"       : "predictive-offline-support-for-assets-you-have-not-used-yet.png",
        "name"        : "Predictive offline support for assets you have not used yet",
        "provider"    : "Medium",
        "publisher"   : "ITNEXT",
        "selectedInto": [],
        "type"        : "Blog Post",
        "url"         : "https://itnext.io/predictive-offline-support-for-assets-you-have-not-used-yet-aeeccccd3754?source=friends_link&sk=e946e0f25f508e6a8cec4136400291a3"
    },
    {
        "author"      : "Tobias Uhlig",
        "authorImage" : "author_TobiasUhlig.jpeg",
        "date"        : "Jan 31, 2022",
        "id"          : 50,
        "image"       : "clean-architectures-your-benefits-of-using-view-controllers.png",
        "name"        : "Clean architectures: Your benefits of using view controllers",
        "provider"    : "Medium",
        "publisher"   : "ITNEXT",
        "selectedInto": [],
        "type"        : "Blog Post",
        "url"         : "https://itnext.io/clean-architectures-your-benefits-of-using-view-controllers-7ce6b00f0ad5?source=friends_link&sk=ebef34d36d5d307c7985ba4dedb261f9"
    },
    {
        "author"      : "Tobias Uhlig",
        "authorImage" : "author_TobiasUhlig.jpeg",
        "date"        : "Jan 17, 2022",
        "id"          : 49,
        "image"       : "scaling-your-micro-frontends-off-the-main-thread.png",
        "name"        : "Scaling your micro-frontends off the main thread",
        "provider"    : "Medium",
        "publisher"   : "ITNEXT",
        "selectedInto": [],
        "type"        : "Blog Post",
        "url"         : "https://itnext.io/scaling-your-micro-frontends-off-the-main-thread-36dedf54c5bf?source=friends_link&sk=04620ee92b04adb4dba22c8ec98d1ef6"
    },
    {
        "author"      : "Tobias Uhlig",
        "authorImage" : "author_TobiasUhlig.jpeg",
        "date"        : "Jan 10, 2022",
        "id"          : 48,
        "image"       : "intercepting-component-state-to-ensure-smooth-animated-transitions.png",
        "name"        : "Intercepting component state to ensure smooth animated transitions",
        "provider"    : "Medium",
        "publisher"   : "ITNEXT",
        "selectedInto": [],
        "type"        : "Blog Post",
        "url"         : "https://itnext.io/intercepting-component-state-to-ensure-smooth-animated-transitions-4facd46414dd?source=friends_link&sk=95a0eaef0e0b15dfc12ddd071479c61c"
    },
    {
        "author"      : "Tobias Uhlig",
        "authorImage" : "author_TobiasUhlig.jpeg",
        "date"        : "Dec 15, 2021",
        "id"          : 47,
        "image"       : "resolving-pitfalls-of-the-ecmascript-class-system.png",
        "name"        : "Resolving pitfalls of the ECMAScript class system",
        "provider"    : "Medium",
        "publisher"   : "ITNEXT",
        "selectedInto": [],
        "type"        : "Blog Post",
        "url"         : "https://itnext.io/resolving-pitfalls-of-the-ecmascript-class-system-856024218399?source=friends_link&sk=9733342654c50d8d618671b754089e1d"
    },
    {
        "author"      : "Tobias Uhlig",
        "authorImage" : "author_TobiasUhlig.jpeg",
        "date"        : "Sep 23, 2021",
        "id"          : 46,
        "image"       : "safari-just-released-support-for-js-modules-inside-the-worker-scope.png",
        "name"        : "Safari (Webkit) just released support for JS modules inside the worker scope",
        "provider"    : "Medium",
        "publisher"   : "ITNEXT",
        "selectedInto": [],
        "type"        : "Blog Post",
        "url"         : "https://itnext.io/safari-webkit-just-released-support-for-js-modules-inside-the-worker-scope-b2d29e67178?source=friends_link&sk=dfabc5dd91430f11e2c49dd10b698544"
    },
    {
        "author"      : "Tobias Uhlig",
        "authorImage" : "author_TobiasUhlig.jpeg",
        "date"        : "Aug 25, 2021",
        "id"          : 45,
        "image"       : "define-a-web-4.0-app-to-be-multi-threaded.png",
        "name"        : "Tutorial: Create your first app in neo v2",
        "provider"    : "Medium",
        "publisher"   : "ITNEXT",
        "selectedInto": [],
        "type"        : "Tutorial",
        "url"         : "https://itnext.io/define-a-web-4-0-app-to-be-multi-threaded-9c495c0d0ef9?source=friends_link&sk=4d143ace05f0e9bbe82babd9433cc822"
    },
    {
        "author"      : "Tobias Uhlig",
        "authorImage" : "author_TobiasUhlig.jpeg",
        "date"        : "Aug 20, 2021",
        "id"          : 44,
        "image"       : "the-best-frontend-development-strategies-in-2022.png",
        "name"        : "The best frontend development strategies in 2022",
        "provider"    : "Medium",
        "publisher"   : "ITNEXT",
        "selectedInto": [],
        "type"        : "Blog Post",
        "url"         : "https://itnext.io/the-best-frontend-development-strategies-in-2022-cb02dd7aa48b?source=friends_link&sk=70ae630fa553df54bdd2acaa531f1767"
    },
    {
        "author"      : "Tobias Uhlig",
        "authorImage" : "author_TobiasUhlig.jpeg",
        "date"        : "Aug 13, 2021",
        "id"          : 43,
        "image"       : "using-material-web-components-within-the-neomjs-application-worker.png",
        "name"        : "Using Material Web Components within the neo.mjs application worker",
        "provider"    : "Medium",
        "publisher"   : "ITNEXT",
        "selectedInto": [],
        "type"        : "Blog Post",
        "url"         : "https://itnext.io/using-material-web-components-within-the-neo-mjs-application-worker-50d3790ea48?source=friends_link&sk=2bca9de4a3ba98b693e7582dcc55a990"
    },
    {
        "author"      : "Tobias Uhlig",
        "authorImage" : "author_TobiasUhlig.jpeg",
        "date"        : "Aug 9, 2021",
        "id"          : 42,
        "image"       : "javascript-development-making-a-web-worker-optional.png",
        "name"        : "JavaScript Development: Making a Web Worker optional",
        "provider"    : "Medium",
        "publisher"   : "ITNEXT",
        "selectedInto": [],
        "type"        : "Blog Post",
        "url"         : "https://itnext.io/javascript-development-making-a-web-worker-optional-f23a13490b28?source=friends_link&sk=63c267c70f36865378a750c772e0a253"
    },
    {
        "author"      : "Tobias Uhlig",
        "authorImage" : "author_TobiasUhlig.jpeg",
        "date"        : "Aug 6, 2021",
        "id"          : 41,
        "image"       : "rendering-3d-offscreen-getting-max-performance-using-canvas-workers.png",
        "name"        : "Rendering 3d offscreen: Getting max performance using canvas workers",
        "provider"    : "Medium",
        "publisher"   : "ITNEXT",
        "selectedInto": [],
        "type"        : "Blog Post",
        "url"         : "https://itnext.io/rendering-3d-offscreen-getting-max-performance-using-canvas-workers-88c207cbcdc2?source=friends_link&sk=7ee0851ff6043c4a79248ff5a20a23fc"
    },
    {
        "author"      : "Tobias Uhlig",
        "authorImage" : "author_TobiasUhlig.jpeg",
        "date"        : "Jun 27, 2021",
        "id"          : 40,
        "image"       : "how-to-create-a-list-containing-checkbox-fields-and-keynav-in-125-lines-of-code.png",
        "name"        : "How to create a List containing CheckBox fields and KeyNav in 125 lines of code",
        "provider"    : "Medium",
        "publisher"   : "ITNEXT",
        "selectedInto": [],
        "type"        : "Blog Post",
        "url"         : "https://itnext.io/how-to-create-a-list-containing-checkbox-fields-and-keynav-in-125-lines-of-code-88b440de2951?source=friends_link&sk=b2d39365dd33f0dd4d3d2715828416cb"
    },
    {
        "author"      : "Tobias Uhlig",
        "authorImage" : "author_TobiasUhlig.jpeg",
        "date"        : "Jun 16, 2021",
        "id"          : 39,
        "image"       : "state-management-two-way-bindings-and-enhanced-binding-formatters.png",
        "name"        : "State management: Two-way bindings and enhanced binding formatters",
        "provider"    : "Medium",
        "publisher"   : "ITNEXT",
        "selectedInto": [],
        "type"        : "Blog Post",
        "url"         : "https://itnext.io/state-management-two-way-bindings-and-enhanced-binding-formatters-f0e9419b7c6b?source=friends_link&sk=6c71c63fcc4df45935418eafa6053978"
    },
    {
        "author"      : "Tobias Uhlig",
        "authorImage" : "author_TobiasUhlig.jpeg",
        "date"        : "Jun 2, 2021",
        "id"          : 38,
        "image"       : "component-development-how-to-create-a-collapsible-fieldset.png",
        "name"        : "Component development: How to create a collapsible Fieldset in neo.mjs",
        "provider"    : "Medium",
        "publisher"   : "ITNEXT",
        "selectedInto": [],
        "type"        : "Blog Post",
        "url"         : "https://itnext.io/component-development-how-to-create-a-collapsible-fieldset-in-neo-mjs-311bf465d829?source=friends_link&sk=48566d3445432f96941132b47737dac0"
    },
    {
        "author"      : "Tobias Uhlig",
        "authorImage" : "author_TobiasUhlig.jpeg",
        "date"        : "May 28, 2021",
        "id"          : 37,
        "image"       : "neo.mjs-v2.2.png",
        "name"        : "neo.mjs v2.2: Main thread MicroLoaders for your Apps",
        "provider"    : "Medium",
        "publisher"   : "ITNEXT",
        "selectedInto": [],
        "type"        : "Blog Post",
        "url"         : "https://itnext.io/neo-mjs-v2-2-main-thread-microloaders-for-your-apps-a8722e32335e?source=friends_link&sk=466312cdeb92ed813be59a1d14d5778c"
    },
    {
        "author"      : "Tobias Uhlig",
        "authorImage" : "author_TobiasUhlig.jpeg",
        "date"        : "May 24, 2021",
        "id"          : 36,
        "image"       : "neo.mjs-nomination.png",
        "name"        : "neo.mjs nominated for “The most exciting Use of Technology”",
        "provider"    : "Medium",
        "publisher"   : "ITNEXT",
        "selectedInto": [],
        "type"        : "Blog Post",
        "url"         : "https://itnext.io/neo-mjs-nominated-for-the-most-exciting-use-of-technology-cd5983debc7b?source=friends_link&sk=6e296e991d09fb7ec98285e90fd50b35"
    },
    {
        "author"      : "Tobias Uhlig",
        "authorImage" : "author_TobiasUhlig.jpeg",
        "date"        : "May 20, 2021",
        "id"          : 35,
        "image"       : "application-based-themed-styling-for-your-components.png",
        "name"        : "Application based themed styling for your components",
        "provider"    : "Medium",
        "publisher"   : "ITNEXT",
        "selectedInto": [],
        "type"        : "Blog Post",
        "url"         : "https://itnext.io/application-based-themed-styling-for-your-components-d8becd1217a9?source=friends_link&sk=3f8304f0ca7f67e6cdc0e3e9a8db6e03"
    },
    {
        "author"      : "Tobias Uhlig",
        "authorImage" : "author_TobiasUhlig.jpeg",
        "date"        : "May 10, 2021",
        "id"          : 34,
        "image"       : "rendering-performance-demo.png",
        "name"        : "Rendering performance demo: 20.000 delta updates per second",
        "provider"    : "Medium",
        "publisher"   : "ITNEXT",
        "selectedInto": [],
        "type"        : "Blog Post",
        "url"         : "https://itnext.io/rendering-performance-demo-20-000-delta-updates-per-second-6f527d8eb8f5?source=friends_link&sk=1261189e91e812659ba6e38819fffe2d"
    },
    {
        "author"      : "Tobias Uhlig",
        "authorImage" : "author_TobiasUhlig.jpeg",
        "date"        : "May 7, 2021",
        "id"          : 33,
        "image"       : "expanding-single-page-apps-into-multiple-browser-windows-part-2.png",
        "name"        : "Expanding Single Page Apps into multiple Browser Windows - Part 2",
        "provider"    : "Medium",
        "publisher"   : "ITNEXT",
        "selectedInto": [],
        "type"        : "Blog Post",
        "url"         : "https://itnext.io/expanding-single-page-apps-into-multiple-browser-windows-part-2-2619ab40361d?source=friends_link&sk=c0b82c4b9ab86633f4e1b950adaff49b"
    },
    {
        "author"      : "Tobias Uhlig",
        "authorImage" : "author_TobiasUhlig.jpeg",
        "date"        : "May 4, 2021",
        "id"          : 32,
        "image"       : "how-to-create-a-file-by-file-custom-scss-build.png",
        "name"        : "How to create a file by file custom SCSS build including dependencies, using postcss and optional css vars",
        "provider"    : "Medium",
        "publisher"   : "ITNEXT",
        "selectedInto": [],
        "type"        : "Blog Post",
        "url"         : "https://itnext.io/how-to-create-a-file-by-file-custom-scss-build-including-dependencies-using-postcss-and-optional-c83f8e5677d8?source=friends_link&sk=1ff756725825df82936b0edb9022c536"
    },
    {
        "author"      : "Tobias Uhlig",
        "authorImage" : "author_TobiasUhlig.jpeg",
        "date"        : "May 1, 2021",
        "id"          : 31,
        "image"       : "new-formatting-concept-for-json-based-virtual-dom.png",
        "name"        : "New formatting concept for JSON based virtual DOM",
        "provider"    : "Medium",
        "publisher"   : "ITNEXT",
        "selectedInto": [],
        "type"        : "Blog Post",
        "url"         : "https://itnext.io/new-formatting-concept-for-json-based-virtual-dom-ee52acc5e04a?source=friends_link&sk=94f69dc71f662e0027118052ceb2db38"
    },
    {
        "author"      : "Tobias Uhlig",
        "authorImage" : "author_TobiasUhlig.jpeg",
        "date"        : "Apr 29, 2021",
        "id"          : 30,
        "image"       : "lazy-loading-for-card-layout-items-and-tabs.png",
        "name"        : "Lazy loading for card layout items and tabs → neo.mjs v2.0.10",
        "provider"    : "Medium",
        "publisher"   : "ITNEXT",
        "selectedInto": [],
        "type"        : "Blog Post",
        "url"         : "https://itnext.io/lazy-loading-for-card-layout-items-and-tabs-neo-mjs-v2-0-10-2bd1c16cd458?source=friends_link&sk=c4651bfff3026ea7fe29f9589bde15b6"
    },
    {
        "author"      : "Tobias Uhlig",
        "authorImage" : "author_TobiasUhlig.jpeg",
        "date"        : "Apr 26, 2021",
        "id"          : 29,
        "image"       : "cross-browser-window-state-management.png",
        "name"        : "Cross browser window state management",
        "provider"    : "Medium",
        "publisher"   : "ITNEXT",
        "selectedInto": [],
        "type"        : "Blog Post",
        "url"         : "https://itnext.io/cross-browser-window-state-management-77bf837b6574?source=friends_link&sk=c164f00034976283f28fd8a0ad361ba2"
    },
    {
        "author"      : "Tobias Uhlig",
        "authorImage" : "author_TobiasUhlig.jpeg",
        "date"        : "Apr 24, 2021",
        "id"          : 28,
        "image"       : "safari-about-to-release-support-for-js-modules-inside-the-worker-scope.png",
        "name"        : "Safari (Webkit) about to release support for JS modules inside the worker scope",
        "provider"    : "Medium",
        "publisher"   : "Level Up Coding",
        "selectedInto": [],
        "type"        : "Blog Post",
        "url"         : "https://levelup.gitconnected.com/safari-webkit-about-to-release-support-for-js-modules-inside-the-worker-scope-9dd33fc20190?source=friends_link&sk=db61a01446ca5a51ee2f932aad9ca890"
    },
    {
        "author"      : "Tobias Uhlig",
        "authorImage" : "author_TobiasUhlig.jpeg",
        "date"        : "Apr 23, 2021",
        "id"          : 27,
        "image"       : "the-webworkers-driven-ui-framework-neomjs-version-2-release-announcement.png",
        "name"        : "The webworkers driven UI framework neo.mjs version 2 release announcement",
        "provider"    : "Medium",
        "publisher"   : "ITNEXT",
        "selectedInto": [],
        "type"        : "Blog Post",
        "url"         : "https://itnext.io/the-webworkers-driven-ui-framework-neo-mjs-version-2-release-announcement-b91b476d6f16?source=friends_link&sk=e6eb21f75475f431ad9215d63a44fb53"
    },
    {
        "author"      : "Tobias Uhlig",
        "authorImage" : "author_TobiasUhlig.jpeg",
        "date"        : "Apr 22, 2021",
        "id"          : 26,
        "image"       : "using-template-literals-to-create-a-binding-engine.png",
        "name"        : "Enhance your frontend state management with view models — Part2",
        "provider"    : "Medium",
        "publisher"   : "JavaScript in Plain English",
        "selectedInto": [],
        "type"        : "Blog Post",
        "url"         : "https://tobiasuhlig.medium.com/enhance-your-frontend-state-management-with-view-models-part2-5a9384bd863c?source=friends_link&sk=e63a577e4118c767de0d289af266482c"
    },
    {
        "author"      : "Tobias Uhlig",
        "authorImage" : "author_TobiasUhlig.jpeg",
        "date"        : "Apr 21, 2021",
        "id"          : 25,
        "image"       : "enhance-your-frontend-state-management-with-view-models.png",
        "name"        : "Enhance your frontend state management with view models",
        "provider"    : "Medium",
        "publisher"   : "ITNEXT",
        "selectedInto": [],
        "type"        : "Blog Post",
        "url"         : "https://itnext.io/enhance-your-frontend-state-management-with-view-models-7bf49e1a0991?source=friends_link&sk=ac04c44c7cd7af4c34068a87b1207c7e"
    },
    {
        "author"      : "Tobias Uhlig",
        "authorImage" : "author_TobiasUhlig.jpeg",
        "date"        : "Mar 22, 2021",
        "id"          : 24,
        "image"       : "web-based-multi-screen-apps-including-drag-drop.png",
        "name"        : "Web based multi-screen apps including drag & drop",
        "provider"    : "Medium",
        "publisher"   : "Geek Culture",
        "selectedInto": [],
        "type"        : "Blog Post",
        "url"         : "https://medium.com/geekculture/web-based-multi-screen-apps-including-drag-drop-5e161da6507b?source=friends_link&sk=3c53f7b9cf882a93fb2929c726bd7721"
    },
    {
        "author"      : "Tobias Uhlig",
        "authorImage" : "author_TobiasUhlig.jpeg",
        "date"        : "Oct 25, 2020",
        "id"          : 23,
        "image"       : "re-sorting-web-based-tabs.png",
        "name"        : "Re-sorting Web-based Tabs like it works in Google Chrome",
        "provider"    : "Medium",
        "publisher"   : "ITNEXT",
        "selectedInto": [],
        "type"        : "Blog Post",
        "url"         : "https://tobiasuhlig.medium.com/re-sorting-web-based-tabs-like-it-works-in-google-chrome-38d749fc8ede?source=friends_link&sk=b01b22b15e68f0671f1a8122dc006274"
    },
    {
        "author"      : "Tobias Uhlig",
        "authorImage" : "author_TobiasUhlig.jpeg",
        "date"        : "Sep 9, 2020",
        "id"          : 22,
        "image"       : "cross-app-bundling-a-different-approach-for-micro-frontends.png",
        "name"        : "Cross App Bundling — A different approach for Micro Frontends",
        "provider"    : "Medium",
        "publisher"   : "The Startup",
        "selectedInto": ["Javascript"],
        "type"        : "Blog Post",
        "url"         : "https://medium.com/@tobiasuhlig/cross-app-bundling-a-different-approach-for-micro-frontends-e4f212b6a9a?source=friends_link&sk=a0b098b4ac792f05348b20cdc007d83c"
    },
    {
        "author"      : "Tom",
        "authorImage" : "author_Tom.jpg",
        "date"        : "Aug 15, 2020",
        "id"          : 21,
        "image"       : "multithreaded-web-apps-beyond-web-worker-by-neo.mjs.jpg",
        "name"        : "Multithreaded Web Apps beyond Web Worker by Neo.mjs",
        "provider"    : "expressFlow",
        "publisher"   : "expressFlow",
        "selectedInto": [],
        "type"        : "Blog Post",
        "url"         : "https://www.expressflow.com/blog/posts/multithreaded-web-app-neo-mjs-pwa-performance"
    },
    {
        "author"      : "Tobias Uhlig",
        "authorImage" : "author_TobiasUhlig.jpeg",
        "date"        : "Aug 7, 2020",
        "id"          : 20,
        "image"       : "your-benefits-of-working-with-json-based-virtual-dom.png",
        "name"        : "Your benefits of working with JSON based virtual DOM",
        "provider"    : "Medium",
        "publisher"   : "DataSeries",
        "selectedInto": ["Javascript"],
        "type"        : "Tutorial",
        "url"         : "https://medium.com/dataseries/your-benefits-of-working-with-json-based-virtual-dom-7318a983da9e?source=friends_link&sk=e513e83c36f05337810e62ab8e5df8e8"
    },
    {
        "author"      : "Tobias Uhlig",
        "authorImage" : "author_TobiasUhlig.jpeg",
        "date"        : "Aug 5, 2020",
        "id"          : 19,
        "image"       : "create-blazing-fast-multithreading-user-interfaces-outside-of-nodejs.png",
        "name"        : "Create blazing fast multithreading User Interfaces outside of nodejs",
        "provider"    : "Medium",
        "publisher"   : "Better Programming",
        "selectedInto": [],
        "type"        : "Blog Post",
        "url"         : "https://medium.com/better-programming/create-blazing-fast-multithreading-user-interfaces-outside-of-nodejs-c4199b0023ec?source=friends_link&sk=f89dcd629317c1ff1f9eed0ac650d86b"
    },
    {
        "author"      : "Tobias Uhlig",
        "authorImage" : "author_TobiasUhlig.jpeg",
        "date"        : "Jul 31, 2020",
        "id"          : 18,
        "image"       : "removing-non-visible-views-from-the-dom.png",
        "name"        : "Removing non visible views from the DOM while still being able to alter their state",
        "provider"    : "Medium",
        "publisher"   : "ITNEXT",
        "selectedInto": ["Javascript"],
        "type"        : "Blog Post",
        "url"         : "https://itnext.io/removing-non-visible-views-from-the-dom-while-still-being-able-to-alter-their-state-dd366ed185ec?source=friends_link&sk=35e7f0bdd65c611b189a47672a398ac1"
    },
    {
        "author"      : "Tobias Uhlig",
        "authorImage" : "author_TobiasUhlig.jpeg",
        "date"        : "Jul 15, 2020",
        "id"          : 17,
        "image"       : "creating-a-responsive-multithreading-website-for-desktop-mobile.png",
        "name"        : "Creating a responsive multithreading Website for Desktop & Mobile",
        "provider"    : "Medium",
        "publisher"   : "ITNEXT",
        "selectedInto": [],
        "type"        : "Release Announcement",
        "url"         : "https://itnext.io/creating-a-responsive-multithreading-website-for-desktop-mobile-8da990ae5bf3?source=friends_link&sk=91bf4b80d62944d54ac28d23d0ca9be3"
    },
    {
        "author"      : "Tobias Uhlig",
        "authorImage" : "author_TobiasUhlig.jpeg",
        "date"        : "Jun 24, 2020",
        "id"          : 16,
        "image"       : "how-to-create-a-webworkers-driven-multithreading-app-part-2.png",
        "name"        : "How to create a webworkers driven multithreading App - Part 2",
        "provider"    : "Medium",
        "publisher"   : "The Startup",
        "selectedInto": ["Javascript"],
        "type"        : "Tutorial",
        "url"         : "https://medium.com/swlh/how-to-create-a-webworkers-driven-multithreading-app-part-2-3c5b3c2d1adb?source=friends_link&sk=cf4b5c0e014fcfd6fc1d9845f4eb3097"
    },
    {
        "author"      : "Tobias Uhlig",
        "authorImage" : "author_TobiasUhlig.jpeg",
        "date"        : "Jun 17, 2020",
        "id"          : 15,
        "image"       : "expanding-single-page-apps-into-multiple-browser-windows.png",
        "name"        : "Expanding Single Page Apps into multiple Browser Windows",
        "provider"    : "Medium",
        "publisher"   : "The Startup",
        "selectedInto": ["Javascript", "Programming", "Software Engineering"],
        "type"        : "Blog Post",
        "url"         : "https://medium.com/swlh/expanding-single-page-apps-into-multiple-browser-windows-e6d9bd155d59?source=friends_link&sk=bbfe1dada95c5674669e463f93360822"
    },
    {
        "author"      : "Tobias Uhlig",
        "authorImage" : "author_TobiasUhlig.jpeg",
        "date"        : "Jun 6, 2020",
        "id"          : 14,
        "image"       : "neo-mjs-v1-2-5-support-for-sharedworkers-including-firefox.png",
        "name"        : "neo.mjs v1.2.5 → Support for SharedWorkers including Firefox",
        "provider"    : "Medium",
        "publisher"   : "The Startup",
        "selectedInto": ["Javascript", "Programming", "Software Engineering"],
        "type"        : "Release Announcement",
        "url"         : "https://medium.com/swlh/neo-mjs-v1-2-5-support-for-sharedworkers-including-firefox-b31f144cea3f?source=friends_link&sk=6bd4d0beb0e095c388153ce8f06aa76f"
    },
    {
        "author"      : "Tobias Uhlig",
        "authorImage" : "author_TobiasUhlig.jpeg",
        "date"        : "Jun 4, 2020",
        "id"          : 13,
        "image"       : "chrome-v83-enables-js-module-support-for-sharedworkers-starting-a-new-era-for-multi-browser.png",
        "name"        : "Chrome v83 enables JS module support for SharedWorkers → Starting a new era for multi Browser Window Apps with neo.mjs",
        "provider"    : "Medium",
        "publisher"   : "The Startup",
        "selectedInto": ["Javascript", "Programming", "Software Engineering"],
        "type"        : "Blog Post",
        "url"         : "https://medium.com/swlh/chrome-v83-enables-js-module-support-for-sharedworkers-starting-a-new-era-for-multi-browser-dbb20366bddf?source=friends_link&sk=5fb6a90658d292a6af5bd30c24cb239d"
    },
    {
        "author"      : "Tobias Uhlig",
        "authorImage" : "author_TobiasUhlig.jpeg",
        "date"        : "May 30, 2020",
        "id"          : 12,
        "image"       : "how-to-create-a-webworkers-driven-multithreading-app-part-1.png",
        "name"        : "How to create a webworkers driven multithreading App — Part 1",
        "provider"    : "Medium",
        "publisher"   : "The Startup",
        "selectedInto": ["Javascript"],
        "type"        : "Tutorial",
        "url"         : "https://medium.com/swlh/how-to-create-a-webworkers-driven-multithreading-app-part-1-fa0cc78a4237?source=friends_link&sk=a10ca85002f5f9c3ee8c69f53c79d95f"
    },
    {
        "author"      : "Tobias Uhlig",
        "authorImage" : "author_TobiasUhlig.jpeg",
        "date"        : "May 28, 2020",
        "id"          : 11,
        "image"       : "the-webworkers-driven-ui-framework-neo-mjs-v1-2-0-release-announcement.png",
        "name"        : "The webworkers driven UI framework: neo.mjs v1.2.0 release announcement",
        "provider"    : "Medium",
        "publisher"   : "Dev Genius",
        "selectedInto": [],
        "type"        : "Release Announcement",
        "url"         : "https://medium.com/dev-genius/the-webworkers-driven-ui-framework-neo-mjs-v1-2-0-release-announcement-a811ebe47252?source=friends_link&sk=8578383b7664e8a2456cbe7726c98aac"
    },
    {
        "author"      : "Tobias Uhlig",
        "authorImage" : "author_TobiasUhlig.jpeg",
        "date"        : "May 24, 2020",
        "id"          : 10,
        "image"       : "bundling-your-webpack-based-build-processes-performance-improvements.png",
        "name"        : "Bundling your Webpack based build processes & performance improvements",
        "provider"    : "Medium",
        "publisher"   : "The Startup",
        "selectedInto": ["Javascript", "Programming"],
        "type"        : "Blog Post",
        "url"         : "https://medium.com/swlh/bundling-your-webpack-based-build-processes-performance-improvements-dd7d0ffdd788?source=friends_link&sk=6b7ae4abdf227ecee6c046b5bc9b14b6"
    },
    {
        "author"      : "Tobias Uhlig",
        "authorImage" : "author_TobiasUhlig.jpeg",
        "date"        : "May 16, 2020",
        "id"          : 9,
        "image"       : "using-js-libraries-inside-a-multithreading-environment.png",
        "name"        : "Using JS libraries inside a multithreading environment",
        "provider"    : "Medium",
        "publisher"   : "codeburst.io",
        "selectedInto": [],
        "type"        : "Blog Post",
        "url"         : "https://codeburst.io/using-js-libraries-inside-a-multithreading-environment-835cd8cbc30b?source=friends_link&sk=39450bea5b2c1812a9adb741d7f9e3af"
    },
    {
        "author"      : "Tobias Uhlig",
        "authorImage" : "author_TobiasUhlig.jpeg",
        "date"        : "Mar 21, 2020",
        "id"          : 8,
        "image"       : "introduction-guide-for-neo-mjs-the-webworkers-driven-ui-framework.png",
        "name"        : "Introduction Guide for neo.mjs — The webworkers driven UI framework",
        "provider"    : "Medium",
        "publisher"   : "codeburst.io",
        "selectedInto": [],
        "type"        : "Blog Post",
        "url"         : "https://codeburst.io/introduction-guide-for-neo-mjs-the-webworkers-driven-ui-framework-c78471715f9d?source=friends_link&sk=b5c818935edaa783c1ec61b76cdc146a"
    },
    {
        "author"      : "Tobias Uhlig",
        "authorImage" : "author_TobiasUhlig.jpeg",
        "date"        : "Mar 11, 2020",
        "id"          : 7,
        "image"       : "javascript-classes-state-management-v2.png",
        "name"        : "Javascript classes:</br>state management v2",
        "provider"    : "Medium",
        "publisher"   : "codeburst.io",
        "selectedInto": [],
        "type"        : "Blog Post",
        "url"         : "https://codeburst.io/javascript-classes-state-management-v2-2df7663de580?source=friends_link&sk=a190aa7e5a2ead4a215a6e5a2de562c6"
    },
    {
        "author"      : "Tobias Uhlig",
        "authorImage" : "author_TobiasUhlig.jpeg",
        "date"        : "Feb 20, 2020",
        "id"          : 6,
        "image"       : "javascript-classes-state-management.png",
        "name"        : "Javascript classes:</br>state management",
        "provider"    : "Medium",
        "publisher"   : "The Startup",
        "selectedInto": ["Javascript"],
        "type"        : "Blog Post",
        "url"         : "https://medium.com/swlh/javascript-classes-state-management-87d66874ac8a?source=friends_link&sk=edd58364135a5848de3e10ac5b2a44d1"
    },
    {
        "author"      : "Tobias Uhlig",
        "authorImage" : "author_TobiasUhlig.jpeg",
        "date"        : "Feb 5, 2020",
        "id"          : 5,
        "image"       : "chrome-v80-release-js-module-support-for-workers.png",
        "name"        : "Chrome v80 release:</br>JS module support for workers",
        "provider"    : "Medium",
        "publisher"   : "codeburst.io",
        "selectedInto": [],
        "type"        : "Blog Post",
        "url"         : "https://codeburst.io/chrome-v80-release-js-module-support-for-workers-a4a9397d194b?source=friends_link&sk=168145da560f59555ccb1f4aaf96298f"
    },
    {
        "author"      : "Tobias Uhlig",
        "authorImage" : "author_TobiasUhlig.jpeg",
        "date"        : "Jan 6, 2020",
        "id"          : 4,
        "image"       : "how-to-create-your-first-neo-mjs-app.png",
        "name"        : "How to create your first neo.mjs App",
        "provider"    : "Medium",
        "publisher"   : "",
        "selectedInto": [],
        "type"        : "Tutorial",
        "url"         : "https://medium.com/@tobiasuhlig/how-to-create-your-first-neo-mjs-app-e68b49c960c7?source=friends_link&sk=30cc526190399c2e875e87bb5359824d"
    },
    {
        "author"      : "Tobias Uhlig",
        "authorImage" : "author_TobiasUhlig.jpeg",
        "date"        : "Jan 3, 2020",
        "id"          : 3,
        "image"       : "release-announcement-npx-neo-app.png",
        "name"        : "Release announcement:</br>npx neo-app",
        "provider"    : "Medium",
        "publisher"   : "",
        "selectedInto": [],
        "type"        : "Release Announcement",
        "url"         : "https://medium.com/@tobiasuhlig/release-announcement-npx-neo-app-190f114e73df?source=friends_link&sk=4f2d1b9d2d08a0e109ffc943f650f58b"
    },
    {
        "author"      : "Tobias Uhlig",
        "authorImage" : "author_TobiasUhlig.jpeg",
        "date"        : "Nov 23, 2019",
        "id"          : 2,
        "image"       : "neo-mjs-the-public-release-announcement.png",
        "name"        : "neo.mjs → The public release announcement",
        "provider"    : "Medium",
        "publisher"   : "codeburst.io",
        "selectedInto": [],
        "type"        : "Release Announcement",
        "url"         : "https://codeburst.io/neo-mjs-the-public-release-announcement-1519255bc8f9?source=friends_link&sk=c7d11dd49bf74463d68cf4ef62a0cb07"
    },
    {
        "author"      : "Tobias Uhlig",
        "authorImage" : "author_TobiasUhlig.jpeg",
        "date"        : "Nov 13, 2019",
        "id"          : 1,
        "image"       : "neo-mjs-documentation-for-your-ui.png",
        "name"        : "neo.mjs: Documentation for your UI",
        "provider"    : "Medium",
        "publisher"   : "",
        "selectedInto": [],
        "type"        : "Blog Post",
        "url"         : "https://medium.com/@tobiasuhlig/neo-mjs-documentation-for-your-ui-77abf9fe8bbe?source=friends_link&sk=f27a4e8b133a02e98a0b01dca8f0cae9"
    }
]
